mcp_kel/GaoDe_mcp.py
mcp_kel/__init__.py
mcp_kel/__main__.py
mcp_kel/base.py
mcp_kel/server.py
mcp_kel/wikipidia_mcp.py
zut_mcp-0.1.14.dist-info/METADATA
zut_mcp-0.1.14.dist-info/WHEEL
zut_mcp-0.1.14.dist-info/entry_points.txt
zut_mcp-0.1.14.dist-info/top_level.txt
zut_mcp-0.1.14.dist-info/RECORD
