Metadata-Version: 2.4
Name: zut-mcp
Version: 0.1.14
Summary: 修改餐饮为df获取, 关键词匹配算法.
Requires-Python: >=3.8
Requires-Dist: mcp[cli]
Requires-Dist: twine
Requires-Dist: wikipedia
Requires-Dist: fuzzywuzzy
Requires-Dist: pandas
